{
    "arbitration": {
      "fields": [
          {
            "type": "String",
            "name": "kurze Beschreibung des Vorfalls",
            "required": true,
            "dependentOn": ""
          },
          {
            "type": "date",
            "name": "Datum des Vorfalls",
            "required": false,
            "dependentOn": ""
          },
          {
            "type": "checkbox",
            "name": "Antrag für jemand anderen",
            "required": true,
            "dependentOn": ""
          },
          {
            "type": "Headline",
            "name": "Adresse geschädigter",
            "required": false,
            "dependentOn": "Antrag für jemand anderen"
          },
          {
            "type": "String",
            "name": "Vorname",
            "required": true,
            "dependentOn": "Antrag für jemand anderen"
          },
          {
            "type": "String",
            "name": "Nachname",
            "required": true,
            "dependentOn": "Antrag für jemand anderen"
          },
          {
            "type": "String",
            "name": "Straße und Hausnummer",
            "required": true,
            "dependentOn": "Antrag für jemand anderen"
          },
          {
            "type": "number",
            "name": "Postleitzahl",
            "required": true,
            "dependentOn": "Antrag für jemand anderen"
          },
          {
            "type": "String",
            "name": "Firma",
            "required": true,
            "dependentOn": ""
          },
          {
            "type": "file",
            "name": "Name",
            "required": true,
            "dependentOn": "Antrag für jemand anderen"
          }
      ]
    }
  }
